ensembler/__init__.py
ensembler/dataset.py
ensembler/ensembler.py
ensembler/job.py
ensembler/sink.py
ensembler/source.py
tests/__init__.py
tests/conftest.py
tests/dataset_test.py
tests/ensembler_test.py
tests/sink_test.py
tests/utils/__init__.py
tests/utils/openapi_utils.py
turing_pyfunc_ensembler_job-1.22.1.dev45.dist-info/METADATA
turing_pyfunc_ensembler_job-1.22.1.dev45.dist-info/WHEEL
turing_pyfunc_ensembler_job-1.22.1.dev45.dist-info/top_level.txt
turing_pyfunc_ensembler_job-1.22.1.dev45.dist-info/RECORD
