Metadata-Version: 2.1
Name: turing-pyfunc-ensembler-job
Version: 1.22.1.dev45
Requires-Python: >=3.8,<3.11
Requires-Dist: cloudpickle ==2.0.0
Requires-Dist: google-cloud-storage >=1.37.0
Requires-Dist: jinja2 ==3.0.3
Requires-Dist: jinjasql ==0.1.8
Requires-Dist: numpy ==1.21.6
Requires-Dist: pandas ==1.3.5
Requires-Dist: py4j ==0.10.9
Requires-Dist: pyarrow <=9.0.0,>=0.14.1
Requires-Dist: pyspark ==3.0.1
Requires-Dist: pyyaml ==6.0
Requires-Dist: setuptools <75
Requires-Dist: turing-sdk ==1.22.1.dev45
